huaweicloudsdkimage/__init__.py
huaweicloudsdkimage/v2/__init__.py
huaweicloudsdkimage/v2/image_async_client.py
huaweicloudsdkimage/v2/image_client.py
huaweicloudsdkimage/v2/model/__init__.py
huaweicloudsdkimage/v2/model/bounding_box.py
huaweicloudsdkimage/v2/model/celebrity_recognition_req.py
huaweicloudsdkimage/v2/model/celebrity_recognition_result_body.py
huaweicloudsdkimage/v2/model/image_main_object_detection_instance.py
huaweicloudsdkimage/v2/model/image_main_object_detection_req.py
huaweicloudsdkimage/v2/model/image_media_tagging_det_instance.py
huaweicloudsdkimage/v2/model/image_media_tagging_det_item_body.py
huaweicloudsdkimage/v2/model/image_media_tagging_det_item_body_i18n_tag.py
huaweicloudsdkimage/v2/model/image_media_tagging_det_req.py
huaweicloudsdkimage/v2/model/image_media_tagging_det_response_result.py
huaweicloudsdkimage/v2/model/image_media_tagging_instance.py
huaweicloudsdkimage/v2/model/image_media_tagging_item_body.py
huaweicloudsdkimage/v2/model/image_media_tagging_item_body_i18n_tag.py
huaweicloudsdkimage/v2/model/image_media_tagging_item_body_i18n_type.py
huaweicloudsdkimage/v2/model/image_media_tagging_req.py
huaweicloudsdkimage/v2/model/image_media_tagging_response_result.py
huaweicloudsdkimage/v2/model/image_tagging_bounding_box.py
huaweicloudsdkimage/v2/model/image_tagging_instance.py
huaweicloudsdkimage/v2/model/image_tagging_item_body.py
huaweicloudsdkimage/v2/model/image_tagging_item_body_i18n_tag.py
huaweicloudsdkimage/v2/model/image_tagging_item_body_i18n_type.py
huaweicloudsdkimage/v2/model/image_tagging_req.py
huaweicloudsdkimage/v2/model/image_tagging_response_result.py
huaweicloudsdkimage/v2/model/recapture_detect_req.py
huaweicloudsdkimage/v2/model/recapture_detect_response_result.py
huaweicloudsdkimage/v2/model/recapture_detect_response_result_detail.py
huaweicloudsdkimage/v2/model/run_celebrity_recognition_request.py
huaweicloudsdkimage/v2/model/run_celebrity_recognition_response.py
huaweicloudsdkimage-3.1.184.dist-info/METADATA
huaweicloudsdkimage-3.1.184.dist-info/WHEEL
huaweicloudsdkimage-3.1.184.dist-info/licenses/LICENSE
huaweicloudsdkimage-3.1.184.dist-info/RECORD
